Metadata-Version: 2.1
Name: convertfiletovoice
Version: 0.1
Summary: convert file to voice
Home-page: https://github.com/user/markokovalua
Download-URL: https://github.com/markokovalua/convertfiletovoice/archieve/refs/tags/v1.0.0.tar.gz
Author: MarkoKoval <marko.koval.work@gmail.com>
Author-email: marko.koval.work@gmail.com
License: MIT
Classifier: Development Status :: 3 - Alpha
Classifier: Intended Audience :: Developers
Classifier: Topic :: Software Development :: Build Tools
Classifier: License :: OSI Approved :: MIT License
Classifier: Programming Language :: Python :: 3
Classifier: Programming Language :: Python :: 3.4
Classifier: Programming Language :: Python :: 3.5
Classifier: Programming Language :: Python :: 3.6
License-File: LICENSE
